MANIFEST.in
README.rst
setup.py
decutils/__init__.py
decutils/core.py
decutils.egg-info/PKG-INFO
decutils.egg-info/SOURCES.txt
decutils.egg-info/dependency_links.txt
decutils.egg-info/top_level.txt