Metadata-Version: 1.1
Name: decutils
Version: 1.0
Summary: Python Decorator Utilities.
Home-page: https://github.com/moisespsena/py_decutils
Author: Moises P. Sena
Author-email: moisespsena@gmail.com
License: BSD
Keywords: utils utilities decorator
Platform: UNKNOWN
Classifier: Development Status :: 4 - Beta
Classifier: Topic :: Utilities
Classifier: Intended Audience :: Developers
Classifier: License :: OSI Approved :: BSD License
Classifier: Operating System :: OS Independent
Classifier: Programming Language :: Python :: 2
Classifier: Programming Language :: Python :: 2.7
Classifier: Programming Language :: Python :: 3
Classifier: Programming Language :: Python :: 3.2
